imapping/__init__.py
imapping-0.1.2.dist-info/WHEEL
imapping-0.1.2.dist-info/METADATA
imapping-0.1.2.dist-info/RECORD
